CHANGES.txt
LICENSE.txt
MANIFEST.in
README.rst
setup.py
pd2hts/__init__.py
pd2hts.egg-info/PKG-INFO
pd2hts.egg-info/SOURCES.txt
pd2hts.egg-info/dependency_links.txt
pd2hts.egg-info/requires.txt
pd2hts.egg-info/top_level.txt
tests/__init__.py
tests/test_pd2hts.py