Metadata-Version: 1.0
Name: pd2hts
Version: 0.1.0
Summary: Read and write Pandas objects from/to Hydrognomon timeseries files
Home-page: https://github.com/openmeteo/pd2hts
Author: Antonis Christofides
Author-email: antonis@antonischristofides.com
License: GPL3
Platform: UNKNOWN
